msiempy/__init__.py
msiempy/__utils__.py
msiempy/__version__.py
msiempy/alarm.py
msiempy/device.py
msiempy/event.py
msiempy/watchlist.py
msiempy/core/__init__.py
msiempy/core/config.py
msiempy/core/query.py
msiempy/core/session.py
msiempy/core/types.py
msiempy/core/utils.py
tests/__init__.py
tests/auth/__init__.py
tests/auth/test_alarm.py
tests/auth/test_device.py
tests/auth/test_event.py
tests/auth/test_session.py
tests/auth/test_watchlist.py
tests/local/__init__.py
tests/local/test_alarm.py
tests/local/test_base.py
tests/local/test_config.py
tests/local/test_getitem.py
tests/local/test_utils.py
msiempy-0.3.5.dist-info/LICENSE
msiempy-0.3.5.dist-info/METADATA
msiempy-0.3.5.dist-info/WHEEL
msiempy-0.3.5.dist-info/top_level.txt
msiempy-0.3.5.dist-info/RECORD
