Metadata-Version: 2.1
Name: msiempy
Version: 0.3.5
Summary: msiempy - McAfee SIEM API Python wrapper
Home-page: https://github.com/mfesiem/msiempy
Maintainer: andywalden, tristanlatr, mathieubeland, and other contributors. 
Maintainer-email: 
License: The MIT License
Keywords: mcafee siem api python wrapper
Platform: UNKNOWN
Classifier: Programming Language :: Python :: 3
Classifier: Intended Audience :: Developers
Classifier: Development Status :: 4 - Beta
Requires-Dist: requests
Requires-Dist: tqdm
Requires-Dist: PTable
Requires-Dist: python-dateutil
Requires-Dist: urllib3
